skipper/__init__.py
skipper/builder.py
skipper/cli.py
skipper/config.py
skipper/git.py
skipper/main.py
skipper/runner.py
skipper/utils.py
skipper/data/skipper-complete.sh
skipper/data/skipper-entrypoint.sh
strato_skipper-2.4.1.dist-info/licenses/LICENSE
strato_skipper-2.4.1.dist-info/METADATA
strato_skipper-2.4.1.dist-info/WHEEL
strato_skipper-2.4.1.dist-info/entry_points.txt
strato_skipper-2.4.1.dist-info/top_level.txt
strato_skipper-2.4.1.dist-info/RECORD
