Metadata-Version: 2.4
Name: strato-skipper
Version: 2.4.1
Summary: Easily dockerize your Git repository
Author-email: Adir Gabai <adir@stratoscale.com>
License: Apache-2
Requires-Python: >=3
License-File: LICENSE
Requires-Dist: PyYAML>=3.11
Requires-Dist: click>=6.7
Requires-Dist: requests>=2.6.0
Requires-Dist: tabulate>=0.7.5
Requires-Dist: six>=1.10.0
Requires-Dist: urllib3>=1.22
Requires-Dist: requests-bearer==0.5.1
Requires-Dist: retry
Requires-Dist: setuptools
Requires-Dist: pbr
Provides-Extra: dev
Requires-Dist: pytest; extra == "dev"
Requires-Dist: pytest-cov; extra == "dev"
Requires-Dist: ruff; extra == "dev"
Dynamic: license-file
